git_punchcard.py
git_punchcard-2.0.4.dist-info/METADATA
git_punchcard-2.0.4.dist-info/WHEEL
git_punchcard-2.0.4.dist-info/entry_points.txt
git_punchcard-2.0.4.dist-info/top_level.txt
git_punchcard-2.0.4.dist-info/RECORD
