Metadata-Version: 2.1
Name: git-punchcard
Version: 2.0.4
Summary: punchcard generator for git commit frequencies
Home-page: https://github.com/coldfix/git-punchcard
Author: Thomas Gläßle
Author-email: thomas@coldfix.de
License: Unlicense
Platform: UNKNOWN
Classifier: Development Status :: 4 - Beta
Classifier: Environment :: Console
Classifier: Intended Audience :: Developers
Classifier: Programming Language :: Python :: 3
Classifier: License :: Public Domain
Classifier: Topic :: Software Development :: Version Control :: Git
Requires-Python: >=3.3
Requires-Dist: numpy
Requires-Dist: matplotlib
Requires-Dist: pytz
Provides-Extra: gui
Requires-Dist: pyqt5 ; extra == 'gui'
